odoo8_addon_dbfilter_from_header-8.0.1.0.1-py2.7-nspkg.pth
odoo8_addon_dbfilter_from_header-8.0.1.0.1.dist-info/top_level.txt
odoo8_addon_dbfilter_from_header-8.0.1.0.1.dist-info/WHEEL
odoo8_addon_dbfilter_from_header-8.0.1.0.1.dist-info/RECORD
odoo8_addon_dbfilter_from_header-8.0.1.0.1.dist-info/metadata.json
odoo8_addon_dbfilter_from_header-8.0.1.0.1.dist-info/DESCRIPTION.rst
odoo8_addon_dbfilter_from_header-8.0.1.0.1.dist-info/METADATA
odoo8_addon_dbfilter_from_header-8.0.1.0.1.dist-info/namespace_packages.txt
odoo_addons/dbfilter_from_header/__openerp__.py
odoo_addons/dbfilter_from_header/__init__.py
odoo_addons/dbfilter_from_header/i18n/dbfilter_from_header.pot
odoo_addons/dbfilter_from_header/static/description/icon.png
